lambda_ai_cloud_api_client/__init__.py
lambda_ai_cloud_api_client/__main__.py
lambda_ai_cloud_api_client/api/__init__.py
lambda_ai_cloud_api_client/api/audit_events/__init__.py
lambda_ai_cloud_api_client/api/audit_events/get_audit_events.py
lambda_ai_cloud_api_client/api/filesystems/__init__.py
lambda_ai_cloud_api_client/api/filesystems/create_filesystem.py
lambda_ai_cloud_api_client/api/filesystems/filesystem_delete.py
lambda_ai_cloud_api_client/api/filesystems/list_filesystems.py
lambda_ai_cloud_api_client/api/firewalls/__init__.py
lambda_ai_cloud_api_client/api/firewalls/create_firewall_ruleset.py
lambda_ai_cloud_api_client/api/firewalls/delete_firewall_ruleset.py
lambda_ai_cloud_api_client/api/firewalls/firewall_rules_list.py
lambda_ai_cloud_api_client/api/firewalls/firewall_rules_set.py
lambda_ai_cloud_api_client/api/firewalls/firewall_rulesets_list.py
lambda_ai_cloud_api_client/api/firewalls/get_firewall_ruleset.py
lambda_ai_cloud_api_client/api/firewalls/get_global_firewall_ruleset.py
lambda_ai_cloud_api_client/api/firewalls/update_firewall_ruleset.py
lambda_ai_cloud_api_client/api/firewalls/update_global_firewall_ruleset.py
lambda_ai_cloud_api_client/api/images/__init__.py
lambda_ai_cloud_api_client/api/images/list_images.py
lambda_ai_cloud_api_client/api/instances/__init__.py
lambda_ai_cloud_api_client/api/instances/get_instance.py
lambda_ai_cloud_api_client/api/instances/launch_instance.py
lambda_ai_cloud_api_client/api/instances/list_instance_types.py
lambda_ai_cloud_api_client/api/instances/list_instances.py
lambda_ai_cloud_api_client/api/instances/post_instance.py
lambda_ai_cloud_api_client/api/instances/restart_instance.py
lambda_ai_cloud_api_client/api/instances/terminate_instance.py
lambda_ai_cloud_api_client/api/ssh_keys/__init__.py
lambda_ai_cloud_api_client/api/ssh_keys/add_ssh_key.py
lambda_ai_cloud_api_client/api/ssh_keys/delete_ssh_key.py
lambda_ai_cloud_api_client/api/ssh_keys/list_ssh_keys.py
lambda_ai_cloud_api_client/cli/__init__.py
lambda_ai_cloud_api_client-2.4.1.dist-info/WHEEL
lambda_ai_cloud_api_client-2.4.1.dist-info/entry_points.txt
lambda_ai_cloud_api_client-2.4.1.dist-info/METADATA
lambda_ai_cloud_api_client-2.4.1.dist-info/RECORD
