Metadata-Version: 2.4
Name: lambda-ai-cloud-api-client
Version: 2.4.1
Summary: A client library for accessing Lambda Cloud API
Keywords: lambda,cloud,api,cli,compute,gpu
Author: Alexander van Eck
Author-email: Alexander van Eck <alexander@x-all.nl>
License-Expression: MIT
Classifier: Development Status :: 5 - Production/Stable
Classifier: Intended Audience :: Developers
Classifier: Intended Audience :: System Administrators
Classifier: License :: OSI Approved :: MIT License
Classifier: Programming Language :: Python :: 3
Classifier: Programming Language :: Python :: 3.10
Classifier: Programming Language :: Python :: 3.11
Classifier: Programming Language :: Python :: 3.12
Classifier: Programming Language :: Python :: 3.13
Classifier: Programming Language :: Python :: 3.14
Classifier: Environment :: Console
Classifier: Topic :: Software Development :: Libraries
Classifier: Topic :: Internet
Requires-Dist: httpx>=0.23.0,<0.29.0
Requires-Dist: attrs>=22.2.0
Requires-Dist: python-dateutil>=2.8.0,<3
Requires-Dist: click>=8.3.1
Requires-Dist: rich>=13.9.4
Requires-Dist: python-dotenv>=1.0.1
Requires-Python: >=3.10
Project-URL: Changelog, https://github.com/alexandervaneck/lambda-ai-cloud-api-client/blob/main/CHANGELOG.md
Project-URL: Homepage, https://github.com/alexandervaneck/lambda-ai-cloud-api-client
Project-URL: Issues, https://github.com/alexandervaneck/lambda-ai-cloud-api-client/issues
Project-URL: Repository, https://github.com/alexandervaneck/lambda-ai-cloud-api-client
